{
  "Radius": 4,
  "Size": {
    "X": 9,
    "Y": 6,
    "Z": 9
  },
  "Layers": [
    {
      "Blocks": "   GGG   , GGEEEGG , GRRRRRG ,GERRRRREG,GERRRRREG,GERRRRREG, GRRRRRG , GGEEEGG ,   GGG   ",
      "Trait": "Standard"
    },
    {
      "Blocks": "   GFG   , GFEEEFG , FRRRRRF ,GERRRRREG,FERRRRREF,GERRRRREG, FRRRRRF , GFEEEFG ,   GFG   ",
      "Trait": "CloneOnce"
    },
    {
      "Blocks": "   GHG   , GHE EHG , HRRRRRH ,GERRRRREG,H RRRRR H,GERRRRREG, HRRRRRH , GHE EHG ,   GHG   ",
      "Trait": "Optional"
    },
    {
      "Blocks": "   GHG   , GHE EHG , HRRRRRH ,GERRRRREG,H RRRRR H,GERRRRREG, HRRRRRH , GHE EHG ,   GHG   ",
      "Trait": "CloneThrice"
    },
    {
      "Blocks": "   GHG   , GHE EHG , HRRRRRH ,GERRRRREG,H RRRRR H,GERRRRREG, HRRRRRH , GHE EHG ,   GHG   ",
      "Trait": "Standard"
    },
    {
      "Blocks": "   GFG   , GFEEEFG , FENNNEF ,GENNNNNEG,FENNNNNEF,GENNNNNEG, FENNNEF , GFEEEFG ,   GFG   ",
      "Trait": "Standard"
    }
  ]
}